fabula/__init__.py
fabula/objectlib.py
fabula/skeel.py
fabula/strategies.py
fabula/remoteModules/__init__.py
fabula/remoteModules/chkPort.py
fabula_py-0.0.4.dist-info/LICENSE
fabula_py-0.0.4.dist-info/METADATA
fabula_py-0.0.4.dist-info/WHEEL
fabula_py-0.0.4.dist-info/top_level.txt
fabula_py-0.0.4.dist-info/RECORD
